projeto/systemVerilog/divisor.sv
module divisor(
    input logic clk, rst, start,
    input logic[15:0] dividendo,
    input logic[15:0] divisor, 
    output logic ready, done_tick,
    output logic[15:0] quociente,
    output logic [15:0] resto
);

    typedef enum {idle, op, done} state_type;
    state_type state_reg, state_next;

    logic [15:0] acumulador_reg, acumulador_next, quociente_reg, quociente_next;

    always_ff @(posedge clk or posedge rst) begin
        if (rst) begin
            state_reg <= idle;
            acumulador_reg <= 0;
            quociente_reg <= 0;
        end else begin
            state_reg <= state_next;
            acumulador_reg <= acumulador_next;
            quociente_reg <= quociente_next;
        end
    end

    always_comb begin
        state_next = state_reg;
        ready = 1'b0;
        done_tick = 1'b0;
        acumulador_next = acumulador_reg;
        quociente_next = quociente_reg;
        resto = acumulador_reg;

        quociente = quociente_reg;
        resto = acumulador_reg;

        case (state_reg)
            idle: begin
                ready = 1'b1;
                if (start) begin
                    if (divisor != 0) begin
                        acumulador_next = dividendo;
                        quociente_next = 0;
                        state_next = op;
                    end else begin
                        state_next = idle;
                    end
                end
            end
            op: begin
                if (acumulador_reg >= divisor) begin
                    acumulador_next = acumulador_reg - divisor;
                    quociente_next = quociente_reg + 1;
                    state_next = op;
                end else begin
                    state_next = done;
                end
            end
            done: begin
                done_tick = 1'b1;
                quociente = quociente_reg;
                resto = acumulador_reg;
                state_next = idle;
            end
            default: begin
                state_next = idle;
            end
        endcase
    end
endmodule

systemVerilog/divisor_tb.sv
`include "divisor.sv"
`timescale 1ns/100ps

module divisor_tb;
    logic clk, rst, start;
    logic[15:0] dividendo;
    logic[15:0] divisor;
    logic ready, done_tick;
    logic[15:0] quociente;
    logic [15:0] resto;
    
    divisor a1 (clk, rst, start, dividendo, divisor, ready, done_tick, quociente, resto);

    initial begin
        $dumpfile("divisor.vcd");
        $dumpvars(0, divisor_tb);
             clk = 1'b0; rst = 1'b1; start = 1'b0; dividendo = 16'd0; divisor = 16'd0;
        #50; rst = 1'b1; start = 1'b1; dividendo = 16'd40; divisor = 16'd2;
        #50; rst = 1'b1; start = 1'b1; dividendo = 16'd30; divisor = 16'd1;
        #50; rst = 1'b1; start = 1'b1; dividendo = 16'd60; divisor = 16'd4;
        #50; rst = 1'b1; start = 1'b1; dividendo = 16'd80; divisor = 16'd5;
        #50; rst = 1'b0; start = 1'b0; dividendo = 16'd30; divisor = 16'd2;
        #50; rst = 1'b0; start = 1'b0; dividendo = 16'd60; divisor = 16'd3;
        #50; rst = 1'b0; start = 1'b0; dividendo = 16'd70; divisor = 16'd4;
        #50; rst = 1'b0; start = 1'b0; dividendo = 16'd80; divisor = 16'd5;
        #50; rst = 1'b1; start = 1'b1; dividendo = 16'd100; divisor = 16'd5;
        #50; rst = 1'b0; start = 1'b1; dividendo = 16'd100; divisor = 16'd5;
        #50; rst = 1'b1; start = 1'b1; dividendo = 16'd150; divisor = 16'd10;
        #50; rst = 1'b0; start = 1'b1; dividendo = 16'd150; divisor = 16'd10;
        #50; rst = 1'b1; start = 1'b1; dividendo = 16'd200; divisor = 16'd10;
        #50; rst = 1'b0; start = 1'b1; dividendo = 16'd200; divisor = 16'd10;
        #50; rst = 1'b1; start = 1'b1; dividendo = 16'd240; divisor = 16'd12;
        #50; rst = 1'b0; start = 1'b1; dividendo = 16'd240; divisor = 16'd12;
        #50; rst = 1'b1; start = 1'b1; dividendo = 16'd300; divisor = 16'd15;
        #50; rst = 1'b0; start = 1'b1; dividendo = 16'd300; divisor = 16'd15;
        #50; rst = 1'b1; start = 1'b1; dividendo = 16'd350; divisor = 16'd17;
        #50; rst = 1'b0; start = 1'b1; dividendo = 16'd350; divisor = 16'd17;
        #50; rst = 1'b1; start = 1'b1; dividendo = 16'd360; divisor = 16'd18;
        #50; rst = 1'b0; start = 1'b1; dividendo = 16'd360; divisor = 16'd18;
        #50; rst = 1'b1; start = 1'b1; dividendo = 16'd400; divisor = 16'd20;
        #50; rst = 1'b0; start = 1'b1; dividendo = 16'd400; divisor = 16'd20;
        #50; rst = 1'b1; start = 1'b1; dividendo = 16'd150; divisor = 16'd7;
        #50; rst = 1'b0; start = 1'b1; dividendo = 16'd150; divisor = 16'd7;
        #50; rst = 1'b1; start = 1'b1; dividendo = 16'd140; divisor = 16'd6;
        #50; rst = 1'b0; start = 1'b1; dividendo = 16'd140; divisor = 16'd6;
        #50; rst = 1'b1; start = 1'b1; dividendo = 16'd200; divisor = 16'd10;
        #50; rst = 1'b0; start = 1'b1; dividendo = 16'd200; divisor = 16'd10;
        #50; rst = 1'b1; start = 1'b1; dividendo = 16'd220; divisor = 16'd11;
        #50; rst = 1'b0; start = 1'b1; dividendo = 16'd220; divisor = 16'd11;
        #50; rst = 1'b1; start = 1'b1; dividendo = 16'd180; divisor = 16'd9;
        #50; rst = 1'b0; start = 1'b1; dividendo = 16'd180; divisor = 16'd9;
        #50; rst = 1'b1; start = 1'b1; dividendo = 16'd80; divisor = 16'd4;
        #50; rst = 1'b0; start = 1'b1; dividendo = 16'd80; divisor = 16'd4;
        #50; rst = 1'b1; start = 1'b1; dividendo = 16'd210; divisor = 16'd10;
        #50; rst = 1'b0; start = 1'b1; dividendo = 16'd210; divisor = 16'd10;
        #50; rst = 1'b1; start = 1'b1; dividendo = 16'd160; divisor = 16'd8;
        #50; rst = 1'b0; start = 1'b1; dividendo = 16'd160; divisor = 16'd8;
        #50; rst = 1'b1; start = 1'b1; dividendo = 16'd190; divisor = 16'd9;
        #50; rst = 1'b0; start = 1'b1; dividendo = 16'd190; divisor = 16'd9;
        #50; rst = 1'b1; start = 1'b1; dividendo = 16'd200; divisor = 16'd10;
        #50; rst = 1'b0; start = 1'b1; dividendo = 16'd200; divisor = 16'd10;
        #50; rst = 1'b1; start = 1'b1; dividendo = 16'd80; divisor = 16'd4;
        #50; rst = 1'b0; start = 1'b1; dividendo = 16'd80; divisor = 16'd4;
        #50; rst = 1'b1; start = 1'b1; dividendo = 16'd140; divisor = 16'd7;
        #50; rst = 1'b0; start = 1'b1; dividendo = 16'd140; divisor = 16'd7;
        #50; rst = 1'b1; start = 1'b1; dividendo = 16'd240; divisor = 16'd12;
        #50; rst = 1'b0; start = 1'b1; dividendo = 16'd240; divisor = 16'd12;
        #50; rst = 1'b1; start = 1'b1; dividendo = 16'd160; divisor = 16'd8;
        #50; rst = 1'b0; start = 1'b1; dividendo = 16'd160; divisor = 16'd8;
        #50; rst = 1'b1; start = 1'b1; dividendo = 16'd100; divisor = 16'd5;
        #50; rst = 1'b0; start = 1'b1; dividendo = 16'd100; divisor = 16'd5;
        #50; rst = 1'b1; start = 1'b1; dividendo = 16'd400; divisor = 16'd20;
        #50; rst = 1'b0; start = 1'b1; dividendo = 16'd400; divisor = 16'd20;
        #50; $finish;      
    end

        always #1 clk = ~clk;

endmodule

systemVerilog/divisor.vcd
$date
	Fri Sep 13 18:55:14 2024
$end
$version
	Icarus Verilog
$end
$timescale
	100ps
$end
$scope module divisor_tb $end
$var wire 16 ! resto [15:0] $end
$var wire 1 " ready $end
$var wire 16 # quociente [15:0] $end
$var wire 1 $ done_tick $end
$var reg 1 % clk $end
$var reg 16 & dividendo [15:0] $end
$var reg 16 ' divisor [15:0] $end
$var reg 1 ( rst $end
$var reg 1 ) start $end
$scope module a1 $end
$var wire 1 % clk $end
$var wire 16 * dividendo [15:0] $end
$var wire 16 + divisor [15:0] $end
$var wire 1 ( rst $end
$var wire 1 ) start $end
$var reg 16 , acumulador_next [15:0] $end
$var reg 16 - acumulador_reg [15:0] $end
$var reg 1 $ done_tick $end
$var reg 16 . quociente [15:0] $end
$var reg 16 / quociente_next [15:0] $end
$var reg 16 0 quociente_reg [15:0] $end
$var reg 1 " ready $end
$var reg 16 1 resto [15:0] $end
$var integer 32 2 state_next [31:0] $end
$var integer 32 3 state_reg [31:0] $end
$upscope $end
$upscope $end
$enddefinitions $end
$comment Show the parameter values. $end
$dumpall
$end
#0
$dumpvars
b0 3
b0 2
b0 1
b0 0
b0 /
b0 .
b0 -
b0 ,
b0 +
b0 *
0)
1(
b0 '
b0 &
0%
0$
b0 #
1"
b0 !
$end
#10
1%
#20
0%
#30
1%
#40
0%
#50
1%
#60
0%
#70
1%
#80
0%
#90
1%
#100
0%
#110
1%
#120
0%
#130
1%
#140
0%
#150
1%
#160
0%
#170
1%
#180
0%
#190
1%
#200
0%
#210
1%
#220
0%
#230
1%
#240
0%
#250
1%
#260
0%
#270
1%
#280
0%
#290
1%
#300
0%
#310
1%
#320
0%
#330
1%
#340
0%
#350
1%
#360
0%
#370
1%
#380
0%
#390
1%
#400
0%
#410
1%
#420
0%
#430
1%
#440
0%
#450
1%
#460
0%
#470
1%
#480
0%
#490
1%
#500
b1 2
b101000 ,
1"
0%
b10 '
b10 +
b101000 &
b101000 *
1)
#510
1%
#520
0%
#530
1%
#540
0%
#550
1%
#560
0%
#570
1%
#580
0%
#590
1%
#600
0%
#610
1%
#620
0%
#630
1%
#640
0%
#650
1%
#660
0%
#670
1%
#680
0%
#690
1%
#700
0%
#710
1%
#720
0%
#730
1%
#740
0%
#750
1%
#760
0%
#770
1%
#780
0%
#790
1%
#800
0%
#810
1%
#820
0%
#830
1%
#840
0%
#850
1%
#860
0%
#870
1%
#880
0%
#890
1%
#900
0%
#910
1%
#920
0%
#930
1%
#940
0%
#950
1%
#960
0%
#970
1%
#980
0%
#990
1%
#1000
b11110 ,
1"
b1 2
0%
b1 '
b1 +
b11110 &
b11110 *
#1010
1%
#1020
0%
#1030
1%
#1040
0%
#1050
1%
#1060
0%
#1070
1%
#1080
0%
#1090
1%
#1100
0%
#1110
1%
#1120
0%
#1130
1%
#1140
0%
#1150
1%
#1160
0%
#1170
1%
#1180
0%
#1190
1%
#1200
0%
#1210
1%
#1220
0%
#1230
1%
#1240
0%
#1250
1%
#1260
0%
#1270
1%
#1280
0%
#1290
1%
#1300
0%
#1310
1%
#1320
0%
#1330
1%
#1340
0%
#1350
1%
#1360
0%
#1370
1%
#1380
0%
#1390
1%
#1400
0%
#1410
1%
#1420
0%
#1430
1%
#1440
0%
#1450
1%
#1460
0%
#1470
1%
#1480
0%
#1490
1%
#1500
b111100 ,
1"
b1 2
0%
b100 '
b100 +
b111100 &
b111100 *
#1510
1%
#1520
0%
#1530
1%
#1540
0%
#1550
1%
#1560
0%
#1570
1%
#1580
0%
#1590
1%
#1600
0%
#1610
1%
#1620
0%
#1630
1%
#1640
0%
#1650
1%
#1660
0%
#1670
1%
#1680
0%
#1690
1%
#1700
0%
#1710
1%
#1720
0%
#1730
1%
#1740
0%
#1750
1%
#1760
0%
#1770
1%
#1780
0%
#1790
1%
#1800
0%
#1810
1%
#1820
0%
#1830
1%
#1840
0%
#1850
1%
#1860
0%
#1870
1%
#1880
0%
#1890
1%
#1900
0%
#1910
1%
#1920
0%
#1930
1%
#1940
0%
#1950
1%
#1960
0%
#1970
1%
#1980
0%
#1990
1%
#2000
b1010000 ,
1"
b1 2
0%
b101 '
b101 +
b1010000 &
b1010000 *
#2010
1%
#2020
0%
#2030
1%
#2040
0%
#2050
1%
#2060
0%
#2070
1%
#2080
0%
#2090
1%
#2100
0%
#2110
1%
#2120
0%
#2130
1%
#2140
0%
#2150
1%
#2160
0%
#2170
1%
#2180
0%
#2190
1%
#2200
0%
#2210
1%
#2220
0%
#2230
1%
#2240
0%
#2250
1%
#2260
0%
#2270
1%
#2280
0%
#2290
1%
#2300
0%
#2310
1%
#2320
0%
#2330
1%
#2340
0%
#2350
1%
#2360
0%
#2370
1%
#2380
0%
#2390
1%
#2400
0%
#2410
1%
#2420
0%
#2430
1%
#2440
0%
#2450
1%
#2460
0%
#2470
1%
#2480
0%
#2490
1%
#2500
b0 ,
1"
b0 2
0%
b10 '
b10 +
b11110 &
b11110 *
0)
0(
#2510
1%
#2520
0%
#2530
1%
#2540
0%
#2550
1%
#2560
0%
#2570
1%
#2580
0%
#2590
1%
#2600
0%
#2610
1%
#2620
0%
#2630
1%
#2640
0%
#2650
1%
#2660
0%
#2670
1%
#2680
0%
#2690
1%
#2700
0%
#2710
1%
#2720
0%
#2730
1%
#2740
0%
#2750
1%
#2760
0%
#2770
1%
#2780
0%
#2790
1%
#2800
0%
#2810
1%
#2820
0%
#2830
1%
#2840
0%
#2850
1%
#2860
0%
#2870
1%
#2880
0%
#2890
1%
#2900
0%
#2910
1%
#2920
0%
#2930
1%
#2940
0%
#2950
1%
#2960
0%
#2970
1%
#2980
0%
#2990
1%
#3000
1"
0%
b11 '
b11 +
b111100 &
b111100 *
#3010
1%
#3020
0%
#3030
1%
#3040
0%
#3050
1%
#3060
0%
#3070
1%
#3080
0%
#3090
1%
#3100
0%
#3110
1%
#3120
0%
#3130
1%
#3140
0%
#3150
1%
#3160
0%
#3170
1%
#3180
0%
#3190
1%
#3200
0%
#3210
1%
#3220
0%
#3230
1%
#3240
0%
#3250
1%
#3260
0%
#3270
1%
#3280
0%
#3290
1%
#3300
0%
#3310
1%
#3320
0%
#3330
1%
#3340
0%
#3350
1%
#3360
0%
#3370
1%
#3380
0%
#3390
1%
#3400
0%
#3410
1%
#3420
0%
#3430
1%
#3440
0%
#3450
1%
#3460
0%
#3470
1%
#3480
0%
#3490
1%
#3500
1"
0%
b100 '
b100 +
b1000110 &
b1000110 *
